tat_cli/__init__.py
tat_cli/__main__.py
tat_cli/tat.py
tat_cli/tat_cli.py
tat_cli-0.0.2.dist-info/LICENSE
tat_cli-0.0.2.dist-info/METADATA
tat_cli-0.0.2.dist-info/WHEEL
tat_cli-0.0.2.dist-info/entry_points.txt
tat_cli-0.0.2.dist-info/top_level.txt
tat_cli-0.0.2.dist-info/RECORD
