Metadata-Version: 2.1
Name: tat_cli
Version: 0.0.2
Summary: Colorize terminal output with regex.
Author-email: salt-die <salt-die@protonmail.com>
License: MIT
Project-URL: repository, https://github.com/salt-die/tat_cli
Classifier: Programming Language :: Python :: 3
Classifier: License :: OSI Approved :: MIT License
Classifier: Operating System :: OS Independent
Requires-Python: >=3.10
License-File: LICENSE
